opcua_tools/__init__.py
opcua_tools/constants.py
opcua_tools/memory_optimizer.py
opcua_tools/navigation.py
opcua_tools/nodes_manipulation.py
opcua_tools/nodeset_generator.py
opcua_tools/nodeset_parser.py
opcua_tools/type_hints.py
opcua_tools/ua_data_types.py
opcua_tools/ua_graph.py
opcua_tools/value_parser.py
opcua_tools/json_parser/__init__.py
opcua_tools/json_parser/namespaces.py
opcua_tools/json_parser/parse.py
opcua_tools/json_parser/type_hints.py
opcua_tools/static/Opc.Ua.NodeSet2.xml
opcua_tools/static/UANodeSet.xsd
opcua_tools/validator/__init__.py
opcua_tools/validator/exceptions.py
opcua_tools/validator/missing_nodes.py
opcua_tools/validator/value_validator.py
opcua_tools-1.8.1.dist-info/licenses/LICENSE
opcua_tools-1.8.1.dist-info/METADATA
opcua_tools-1.8.1.dist-info/WHEEL
opcua_tools-1.8.1.dist-info/top_level.txt
opcua_tools-1.8.1.dist-info/RECORD
