Metadata-Version: 2.4
Name: opcua-tools
Version: 1.8.1
Summary: OPCUA Tools for Python using Pandas DataFrames
Home-page: https://github.com/PrediktorAS/opcua-tools
Author: TGS Prediktor AS
Author-email: dawid.makar@tgs.com
License: Apache License 2.0
Classifier: License :: OSI Approved :: Apache Software License
Classifier: Programming Language :: Python :: 3
Classifier: Programming Language :: Python :: 3.8
Classifier: Programming Language :: Python :: 3.9
Classifier: Programming Language :: Python :: 3.10
Classifier: Programming Language :: Python :: 3.11
Classifier: Programming Language :: Python :: 3.12
License-File: LICENSE
Requires-Dist: lxml<6.0,>=5.3.0
Requires-Dist: xmltodict>=0.14.2
Requires-Dist: numpy<2.0,>=1.26.2
Requires-Dist: pandas<2.2.0,>=2.0.0
Requires-Dist: scipy<2.0,>=1.14.1
Dynamic: author
Dynamic: author-email
Dynamic: classifier
Dynamic: description
Dynamic: description-content-type
Dynamic: home-page
Dynamic: license
Dynamic: license-file
Dynamic: requires-dist
Dynamic: summary
